{
  "Frances Coronel": {
    "name": "Frances Coronel",
    "title": "Executive Director",
    "type": "Part-Time Staff",
    "image": "/assets/img/team/frances-coronel.jpg",
    "linkedin": "https://linkedin.com/in/francescoronel"
  },
  "Mary Ramirez": {
    "name": "Mary Ramirez",
    "title": "Partnerships Director",
    "type": "Part-Time Staff",
    "image": "/assets/img/team/mary-ramirez.png",
    "linkedin": "https://www.linkedin.com/in/marybramirez/"
  },
  "Cat Martinez": {
    "name": "Cat Martinez",
    "title": "Partnerships Director",
    "type": "Part-Time Staff",
    "image": "/assets/img/team/cat-martinez.jpeg",
    "linkedin": "https://www.linkedin.com/in/cathmartinez/"
  },
  "Sal Ramirez": {
    "name": "Sal Ramirez",
    "title": "Events Director",
    "type": "Part-Time Staff",
    "image": "/assets/img/team/sal-ramirez.jpeg",
    "linkedin": "https://www.linkedin.com/in/salramirez/"
  },
  "Francisco Cruz-Mendoza": {
    "name": "Francisco Cruz-Mendoza",
    "title": "Chapter Community Director",
    "type": "Volunteer",
    "image": "/assets/img/team/francisco-cruz-mendoza.jpeg",
    "linkedin": "https://www.linkedin.com/in/franciscocrz"
  },
  "Jasmin Gonzalez": {
    "name": "Jasmin Gonzalez",
    "title": "Marketing Director",
    "type": "Part-Time Staff",
    "image": "/assets/img/team/jasmin-gonzalez.jpg",
    "linkedin": "https://www.linkedin.com/in/gonzalezjasmin/"
  }
}
